{
  "people": 
	[
		{"idPhoto":"1","flickrUser":"7394371@N06","flickrPhoto":"534440527","nameProduct":"Acelga"},{"idPhoto":"2","flickrUser":"bossbob50","flickrPhoto":"5183688674","nameProduct":"Ajo"},{"idPhoto":"3","flickrUser":"dos82","flickrPhoto":"455129787","nameProduct":"Alcachofa"},{"idPhoto":"4","flickrUser":"minidesastre","flickrPhoto":"3669837138","nameProduct":"Apio"},{"idPhoto":"5","flickrUser":"dabeat","flickrPhoto":"446084600","nameProduct":"Ajo tierno"},{"idPhoto":"6","flickrUser":"bambolia","flickrPhoto":"496161681","nameProduct":"Achicoria"},{"idPhoto":"7","flickrUser":"themarmot","flickrPhoto":"1677987530","nameProduct":"Berenjena"},{"idPhoto":"8","flickrUser":"chinesesouppot","flickrPhoto":"5845332049","nameProduct":"Berro"},{"idPhoto":"9","flickrUser":"calafellvalo","flickrPhoto":"4122009864","nameProduct":"Boniato"},{"idPhoto":"10","flickrUser":"37884983@N03","flickrPhoto":"3643886883","nameProduct":"Br\u00f3coli"},{"idPhoto":"11","flickrUser":"graibeard","flickrPhoto":"3318366094","nameProduct":"Calabac\u00edn"},{"idPhoto":"12","flickrUser":"24423474@N08","flickrPhoto":"6402158459","nameProduct":"Calabaza"},{"idPhoto":"13","flickrUser":"lablasco","flickrPhoto":"4583606147","nameProduct":"Cardo"},{"idPhoto":"14","flickrUser":"mundoo","flickrPhoto":"2261728337","nameProduct":"Cebolla"},{"idPhoto":"15","flickrUser":"pixeleden","flickrPhoto":"4099278368","nameProduct":"Cebolla roja"},{"idPhoto":"16","flickrUser":"juantiagues","flickrPhoto":"3460087669","nameProduct":"Cebolleta"},{"idPhoto":"17","flickrUser":"liopic","flickrPhoto":"5356918096","nameProduct":"Can\u00f3nigo"},{"idPhoto":"18","flickrUser":"johnsu01","flickrPhoto":"3286038831","nameProduct":"Coles de Bruselas"},{"idPhoto":"19","flickrUser":"arsheffield","flickrPhoto":"5403924470","nameProduct":"Col Lombarda"},{"idPhoto":"20","flickrUser":"nsalt","flickrPhoto":"4095119171","nameProduct":"Coliflor"},{"idPhoto":"21","flickrUser":"42255449@N00","flickrPhoto":"7015155275","nameProduct":"Chirivias"},{"idPhoto":"22","flickrUser":"richardnorth","flickrPhoto":"7179366254","nameProduct":"Endivia"},{"idPhoto":"23","flickrUser":"jlastras","flickrPhoto":"3177948910","nameProduct":"Escarola"},{"idPhoto":"24","flickrUser":"peterpics924","flickrPhoto":"523494612","nameProduct":"Esp\u00e1rrago"},{"idPhoto":"25","flickrUser":"jlastras","flickrPhoto":"2690749144","nameProduct":"Esp\u00e1rrago verde"},{"idPhoto":"26","flickrUser":"42614915@N00","flickrPhoto":"2342471072","nameProduct":"Espinaca"},{"idPhoto":"27","flickrUser":"hatm","flickrPhoto":"2811995750","nameProduct":"Guisantes"},{"idPhoto":"28","flickrUser":"syrenmuse","flickrPhoto":"3528956443","nameProduct":"Grelo"},{"idPhoto":"29","flickrUser":"bilobicles","flickrPhoto":"283761044","nameProduct":"Habas"},{"idPhoto":"30","flickrUser":"procsilas","flickrPhoto":"2931511584","nameProduct":"Jud\u00eda verde"},{"idPhoto":"31","flickrUser":"fcastellanos","flickrPhoto":"5448803362","nameProduct":"Lechuga"},{"idPhoto":"32","flickrUser":"ponto-e-virgula","flickrPhoto":"5736757691","nameProduct":"Nabos"},{"idPhoto":"33","flickrUser":"27369469@N08","flickrPhoto":"2660160225","nameProduct":"Pepino"},{"idPhoto":"34","flickrUser":"martius","flickrPhoto":"6577125353","nameProduct":"Pimiento"},{"idPhoto":"35","flickrUser":"elbeewa","flickrPhoto":"8106511329","nameProduct":"Puerro"},{"idPhoto":"36","flickrUser":"buzzhoffman","flickrPhoto":"4499242134","nameProduct":"Patata"},{"idPhoto":"37","flickrUser":"buzzhoffman","flickrPhoto":"4499242134","nameProduct":"Patatas nuevas"},{"idPhoto":"38","flickrUser":"skene","flickrPhoto":"464760375","nameProduct":"Rabano"},{"idPhoto":"39","flickrUser":"satrina0","flickrPhoto":"745522508","nameProduct":"Remolacha"},{"idPhoto":"40","flickrUser":"bg","flickrPhoto":"5515711680","nameProduct":"Repollo"},{"idPhoto":"41","flickrUser":"martius","flickrPhoto":"5015319185","nameProduct":"Setas"},{"idPhoto":"42","flickrUser":"51708886@N03","flickrPhoto":"5099572469","nameProduct":"N\u00edscalos"},{"idPhoto":"43","flickrUser":"photon_de","flickrPhoto":"2700323949","nameProduct":"Tomate"},{"idPhoto":"44","flickrUser":"sweetbeetandgreenbean","flickrPhoto":"4286053691","nameProduct":"S\u00e9samo"},{"idPhoto":"45","flickrUser":"clcphoto","flickrPhoto":"4664734666","nameProduct":"Zanahoria"},{"idPhoto":"46","flickrUser":"youasamachine","flickrPhoto":"7916970314","nameProduct":"Aguacates"},{"idPhoto":"47","flickrUser":"atzimbatm","flickrPhoto":"3568507279","nameProduct":"Almendra"},{"idPhoto":"48","flickrUser":"martius","flickrPhoto":"5887231521","nameProduct":"Albaricoques"},{"idPhoto":"49","flickrUser":"martius","flickrPhoto":"4780865204","nameProduct":"Brevas"},{"idPhoto":"50","flickrUser":"paparazzi_culiao","flickrPhoto":"477290809","nameProduct":"Caqui"},{"idPhoto":"51","flickrUser":"cookbookman","flickrPhoto":"6896612369","nameProduct":"Casta\u00f1as"},{"idPhoto":"52","flickrUser":"malteahrens","flickrPhoto":"5329917980","nameProduct":"Cerezas"},{"idPhoto":"53","flickrUser":"martius","flickrPhoto":"3407637758","nameProduct":"Ciruelas"},{"idPhoto":"54","flickrUser":"ryangreenberg","flickrPhoto":"70148951","nameProduct":"Chirimoya"},{"idPhoto":"55","flickrUser":"35832540@N03","flickrPhoto":"3330701660","nameProduct":"Coco"},{"idPhoto":"56","flickrUser":"37884983@N03","flickrPhoto":"3690890800","nameProduct":"Frambuesas"},{"idPhoto":"57","flickrUser":"sanchom","flickrPhoto":"2842525085","nameProduct":"Fresas"},{"idPhoto":"58","flickrUser":"mrbonhomme","flickrPhoto":"2364707162","nameProduct":"Fresones"},{"idPhoto":"59","flickrUser":"mrbonhomme","flickrPhoto":"2364707162","nameProduct":"Fres\u00f3n de Palos"},{"idPhoto":"60","flickrUser":"cafeconlecheporfavor","flickrPhoto":"52644712","nameProduct":"Granadas"},{"idPhoto":"61","flickrUser":"akane86","flickrPhoto":"6860405232","nameProduct":"D\u00e1tiles"},{"idPhoto":"62","flickrUser":"calafellvalo","flickrPhoto":"3855840471","nameProduct":"Higos"},{"idPhoto":"63","flickrUser":"justusbluemer","flickrPhoto":"6042946191","nameProduct":"Kiwis"},{"idPhoto":"64","flickrUser":"fmaul","flickrPhoto":"69667785","nameProduct":"Limas"},{"idPhoto":"65","flickrUser":"sugarhiccuphiccup","flickrPhoto":"4808604692","nameProduct":"Lim\u00f3n"},{"idPhoto":"66","flickrUser":"jonycunha","flickrPhoto":"4287334799","nameProduct":"Litchi"},{"idPhoto":"67","flickrUser":"diocrio","flickrPhoto":"2627962459","nameProduct":"Grosellas"},{"idPhoto":"68","flickrUser":"chamoestudio","flickrPhoto":"5515325581","nameProduct":"Mandarina"},{"idPhoto":"69","flickrUser":"dihlie","flickrPhoto":"3597323021","nameProduct":"Mango"},{"idPhoto":"70","flickrUser":"martius","flickrPhoto":"6170108218","nameProduct":"Manzana"},{"idPhoto":"71","flickrUser":"arionfoto","flickrPhoto":"4131727286","nameProduct":"Maracuya o Fruta de la pasi\u00f3n"},{"idPhoto":"72","flickrUser":"akane86","flickrPhoto":"6370796889","nameProduct":"Manzana reineta"},{"idPhoto":"73","flickrUser":"bcostin","flickrPhoto":"28109150","nameProduct":"Melocot\u00f3n"},{"idPhoto":"74","flickrUser":"cookthink","flickrPhoto":"205157535","nameProduct":"Mel\u00f3n"},{"idPhoto":"75","flickrUser":"fotoburra","flickrPhoto":"367949840","nameProduct":"Membrillos"},{"idPhoto":"76","flickrUser":"landahlauts","flickrPhoto":"4101192400","nameProduct":"Naranja"},{"idPhoto":"77","flickrUser":"turatti","flickrPhoto":"6916329330","nameProduct":"Nectarina"},{"idPhoto":"78","flickrUser":"damianvila","flickrPhoto":"977207883","nameProduct":"Nueces"},{"idPhoto":"79","flickrUser":"calafellvalo","flickrPhoto":"3723918048","nameProduct":"N\u00edsperos"},{"idPhoto":"80","flickrUser":"tangaroo","flickrPhoto":"506582947","nameProduct":"Papaya"},{"idPhoto":"81","flickrUser":"topsynette","flickrPhoto":"7725408884","nameProduct":"Paraguaya"},{"idPhoto":"82","flickrUser":"mpeinadopa","flickrPhoto":"4845997516","nameProduct":"Pera amarilla y de agua"},{"idPhoto":"83","flickrUser":"mpeinadopa","flickrPhoto":"4845997516","nameProduct":"Pera de San Juan"},{"idPhoto":"84","flickrUser":"stankuns","flickrPhoto":"2648857215","nameProduct":"Pl\u00e1tano"},{"idPhoto":"85","flickrUser":"purecaffeine","flickrPhoto":"3822269964","nameProduct":"Pi\u00f1a"},{"idPhoto":"86","flickrUser":"stefanvds","flickrPhoto":"3260956205","nameProduct":"Pomelos"},{"idPhoto":"87","flickrUser":"durica","flickrPhoto":"1062402066","nameProduct":"Sand\u00eda"},{"idPhoto":"88","flickrUser":"a_t_ljungberg","flickrPhoto":"251602869","nameProduct":"Uvas"},{"idPhoto":"89","flickrUser":"zest-pk","flickrPhoto":"923930277","nameProduct":"Uva de Aledo"}
	]  
}
